__init__.py
jeremydimond_pytesthelpers-1.0.4.dist-info/licenses/LICENSE
pytesthelpers/__init__.py
pytesthelpers/exceptionhandling.py
pytesthelpers/parametrize.py
jeremydimond_pytesthelpers-1.0.4.dist-info/METADATA
jeremydimond_pytesthelpers-1.0.4.dist-info/WHEEL
jeremydimond_pytesthelpers-1.0.4.dist-info/top_level.txt
jeremydimond_pytesthelpers-1.0.4.dist-info/RECORD
